CHANGE.rst
KNOWN_ISSUES.rst
MANIFEST.in
PLATFORMS.rst
README.rst
setup.py
packy_agent/__init__.py
packy_agent/constants.py
packy_agent/exceptions.py
packy_agent/requirements.txt
packy_agent.egg-info/PKG-INFO
packy_agent.egg-info/SOURCES.txt
packy_agent.egg-info/dependency_links.txt
packy_agent.egg-info/entry_points.txt
packy_agent.egg-info/not-zip-safe
packy_agent.egg-info/top_level.txt
packy_agent/cli/activate.py
packy_agent/cli/http.py
packy_agent/cli/migrate1to2.py
packy_agent/cli/ping.py
packy_agent/cli/set_dhcp.py
packy_agent/cli/settings.py
packy_agent/cli/traceroute.py
packy_agent/cli/version.py
packy_agent/cli/welcome.py
packy_agent/clients/local_storage.py
packy_agent/clients/packy_agent_worker.py
packy_agent/clients/packy_communication.py
packy_agent/clients/packy_server.py
packy_agent/clients/sentry.py
packy_agent/configuration/alembic.ini
packy_agent/configuration/base.py
packy_agent/configuration/settings.py
packy_agent/configuration/sources/base.py
packy_agent/configuration/sources/defaults.py
packy_agent/configuration/sources/defaults_dict.py
packy_agent/configuration/sources/environment.py
packy_agent/configuration/sources/file.py
packy_agent/configuration/sources/key_value_storage.py
packy_agent/configuration/sources/server.py
packy_agent/configuration/templates/nginx.conf.j2
packy_agent/configuration/templates/nginx_alpine.conf.j2
packy_agent/configuration/templates/supervisord.conf.j2
packy_agent/configuration/templates/uwsgi.ini.j2
packy_agent/configuration/templates/control-scripts/ubuntu/initd.sh.j2
packy_agent/configuration/templates/control-scripts/ubuntu/packy.service.j2
packy_agent/configuration/templates/network/ubuntu-debian/dhcp
packy_agent/configuration/templates/network/ubuntu-debian/static
packy_agent/console/app.py
packy_agent/console/run.py
packy_agent/console/wsgi.py
packy_agent/console/forms/__init__.py
packy_agent/console/forms/action.py
packy_agent/console/forms/activate.py
packy_agent/console/forms/activate_extra.py
packy_agent/console/forms/login.py
packy_agent/console/forms/network.py
packy_agent/console/static/css/style.min.css
packy_agent/console/static/img/logo-fav.png
packy_agent/console/static/img/logo.png
