Metadata-Version: 1.0
Name: packy-agent
Version: 2.0.17
Summary: Packy Agent
Home-page: UNKNOWN
Author: UNKNOWN
Author-email: UNKNOWN
License: UNKNOWN
Platform: UNKNOWN
